MANIFEST.in
Makefile
PKGBUILD
README.txt
middlestorm.py
setup.py
middlestorm.egg-info/PKG-INFO
middlestorm.egg-info/SOURCES.txt
middlestorm.egg-info/dependency_links.txt
middlestorm.egg-info/entry_points.txt
middlestorm.egg-info/requires.txt
middlestorm.egg-info/top_level.txt
middlestorm.egg-info/zip-safe
tests/test_wsgi.py