Metadata-Version: 1.0
Name: middlestorm
Version: 0.8.1
Summary: Middleware for use Storm ORM in WSGI applications
Home-page: http://pypi.python.org/pypi/middlestorm
Author: Vsevolod Balashov
Author-email: vsevolod@balashov.name
License: LGPL 2.1
Keywords: wsgi middleware decorator storm orm dbms db postgres mysql sqlite web webdev www
Platform: UNKNOWN
Classifier: Development Status :: 4 - Beta
Classifier: Environment :: Web Environment
Classifier: Intended Audience :: Developers
Classifier: License :: OSI Approved :: GNU Library or Lesser General Public License (LGPL)
Classifier: Natural Language :: Russian
Classifier: Operating System :: OS Independent
Classifier: Programming Language :: Python
Classifier: Topic :: Database :: Front-Ends
Classifier: Topic :: Internet :: WWW/HTTP :: WSGI :: Middleware
